PyHP3577A/PyHP3577A.py
PyHP3577A/__init__.py
PyHP3577A-0.1.dist-info/LICENSE
PyHP3577A-0.1.dist-info/METADATA
PyHP3577A-0.1.dist-info/WHEEL
PyHP3577A-0.1.dist-info/top_level.txt
PyHP3577A-0.1.dist-info/RECORD
