Metadata-Version: 2.1
Name: PyHP3577A
Version: 0.1
Summary: module to easily contorl a Rigol DS1000x series scope and quickly build a measurement setup
Home-page: https://github.com/Minu-IU3IRR/PyHP3577A
Author: Manuel Minutello
License: MIT
License-File: LICENSE
